Codigos Calculadora/multiplicador/rtl/control_mult.v
// Acà se muestra el FSM para control del multiplicador
// LOs distintos estados son: IDLE, LOAD, CHECK, ADD, SHIFT, DONE
module control_mult (
    input wire clk,
    input wire reset,
    input wire start,
    input wire B_bit0,
    input wire count_zero,
    output reg load,
    output reg add,
    output reg shift,
    output reg clear_P,
    output reg dec_count,
    output reg busy,
    output reg done
);

    // Acà tengo la definicion de estados
    localparam [2:0] 
        IDLE    = 3'd0,
        LOAD    = 3'd1,
        CHECK   = 3'd2,
        ADD     = 3'd3,
        SHIFT   = 3'd4,
        DONE_ST = 3'd5;
    
    reg [2:0] state, next_state;
    
    // Esta secciòn serìa correspondiente al registro de estado
    always @(posedge clk or posedge reset) begin
        if (reset)
            state <= IDLE;
        else
            state <= next_state;
    end
    
    // En esta parte se encuentra la lògica combinacional - siguiente estado
    always @(*) begin
        next_state = state;
        
        case (state)
            IDLE: begin
                if (start)
                    next_state = LOAD;
            end
            
            LOAD: begin
                next_state = CHECK;
            end
            
            CHECK: begin
                if (B_bit0)
                    next_state = ADD;
                else
                    next_state = SHIFT;
            end
            
            ADD: begin
                next_state = SHIFT;
            end
            
            SHIFT: begin
                if (count_zero)
                    next_state = DONE_ST;
                else
                    next_state = CHECK;
            end
            
            DONE_ST: begin
                next_state = IDLE;
            end
            
            default: begin
                next_state = IDLE;
            end
        endcase
    end
    
    // Aca lo que tengo es la combinacional - salidas
    always @(*) begin
        // Valores por defecto
        load = 1'b0;
        add = 1'b0;
        shift = 1'b0;
        clear_P = 1'b0;
        dec_count = 1'b0;
        busy = 1'b0;
        done = 1'b0;
        
        case (state)
            IDLE: begin
                busy = 1'b0;
                done = 1'b0;
            end
            
            LOAD: begin
                load = 1'b1;
                clear_P = 1'b1;
                busy = 1'b1;
            end
            
            CHECK: begin
                busy = 1'b1;
            end
            
            ADD: begin
                add = 1'b1;
                busy = 1'b1;
            end
            
            SHIFT: begin
                shift = 1'b1;
                dec_count = 1'b1;
                busy = 1'b1;
            end
            
            DONE_ST: begin
                done = 1'b1;
                busy = 1'b0;
            end
            
            default: begin
                busy = 1'b0;
                done = 1'b0;
            end
        endcase
    end

endmodule

Codigos Calculadora/entrega_final/rtl/dp_mult.v
// En el presente archivo tengo el datapath del multiplicador
module dp_mult (
    input wire clk,
    input wire reset,
    input wire [7:0] A_in,
    input wire [7:0] B_in,
    input wire load,
    input wire add,
    input wire shift,
    input wire clear_P,
    input wire dec_count,
    output reg [15:0] P,
    output wire [7:0] A_reg_out,
    output wire [7:0] B_reg_out,
    output wire B_bit0,
    output wire count_zero
);

    reg [15:0] A_reg;  
    reg [7:0] B_reg;
    reg [3:0] count;
    
    assign A_reg_out = A_reg[7:0];  
    assign B_reg_out = B_reg;
    assign B_bit0 = B_reg[0];
    assign count_zero = (count == 4'd0);
    
    always @(posedge clk or posedge reset) begin
        if (reset) begin
            A_reg <= 16'd0;
            B_reg <= 8'd0;
            P <= 16'd0;
            count <= 4'd0;
        end 
        else begin
            if (load) begin
                A_reg <= {8'd0, A_in};  // EN esta parte se carga con extensión a 16 bits
                B_reg <= B_in;
                count <= 4'd8;
            end
            
            if (clear_P) 
                P <= 16'd0;
            
            if (add) 
                P <= P + A_reg;  //Aqui especificamente se lleva a cabo lo que serìa la suma directa
            
            if (shift) begin
                A_reg <= A_reg << 1;  //Este es el esplazamiento de 16 bits
                B_reg <= B_reg >> 1;
            end
            
            if (dec_count) 
                count <= count - 1;
        end
    end

endmodule

Codigos Calculadora/entrega_final/rtl/mult_top.v

// Este es el mòdulo superior del multiplicador secuencial 8x8
// Lo que hace es que conecta la máquina de estados con el camino
// de datos. La FSM genera las señales de control y el 
// datapath hace las operaciones las cuales vedrìan siedo:
//
//  - la carga de operandos
//  - la suma condicional
//  - los respectivos desplazamientos
//  - y el contador de iteraciones
//
// El resultado final aparece en P y la FSM indica cuando
// el cálculo ya se terminó.
module mult_top (
    input  wire        clk,
    input  wire        reset,
    input  wire        start,
    input  wire [7:0]  A,
    input  wire [7:0]  B,
    output wire [15:0] P,
    output wire        busy,
    output wire        done
);

    // Estas son mis señales internas entre control y datapath
    wire load;
    wire add;
    wire shift;
    wire clear_P;
    wire dec_count;
    wire B_bit0;
    wire count_zero;

 
    // Esta parte corresponde al camino de datos
    dp_mult datapath (
        .clk(clk),
        .reset(reset),
        .A_in(A),
        .B_in(B),
        .load(load),
        .add(add),
        .shift(shift),
        .clear_P(clear_P),
        .dec_count(dec_count),
        .P(P),
        .A_reg_out(),
        .B_reg_out(),
        .B_bit0(B_bit0),
        .count_zero(count_zero)
    );


    // Maq de control
    control_mult fsm (
        .clk(clk),
        .reset(reset),
        .start(start),
        .B_bit0(B_bit0),
        .count_zero(count_zero),
        .load(load),
        .add(add),
        .shift(shift),
        .clear_P(clear_P),
        .dec_count(dec_count),
        .busy(busy),
        .done(done)
    );

endmodule

Codigos Calculadora/multiplicador/sim/tb_mult.v
`timescale 1ns/1ps

module tb_mult;

    reg clk;
    reg reset;
    reg start;
    reg [7:0] A;
    reg [7:0] B;
    wire [15:0] P;
    wire busy;
    wire done;
    
    mult_top dut (
        .clk(clk),
        .reset(reset),
        .start(start),
        .A(A),
        .B(B),
        .P(P),
        .busy(busy),
        .done(done)
    );
    
    initial begin
        clk = 0;
        forever #10 clk = ~clk;
    end
    
    initial begin
        reset = 1;
        start = 0;
        A = 8'd0;
        B = 8'd0;
        
        $dumpfile("multiplicador.vcd");
        $dumpvars(0, tb_mult);
        
        $display("Inicio de pruebas");
        
        #50;
        reset = 0;
        #20;
        
        // Acà està el test 1: 5 x 3
        $display("Test 1: 5 x 3");
        A = 8'd5;
        B = 8'd3;
        start = 1;
        #20;
        start = 0;
        wait(done == 1);
        #20;
        
        if (P == 16'd15)
            $display("PASS - Resultado: %d", P);
        else
            $display("FAIL - Esperado: 15, Obtenido: %d", P);
        
        #100;
        
        // Este serìa el test 2: 12 x 8
        $display("Test 2: 12 x 8");
        A = 8'd12;
        B = 8'd8;
        start = 1;
        #20;
        start = 0;
        wait(done == 1);
        #20;
        
        if (P == 16'd96)
            $display("PASS - Resultado: %d", P);
        else
            $display("FAIL - Esperado: 96, Obtenido: %d", P);
        
        #100;
        
        // Acà tenemos el test 3: 255 x 255
        $display("Test 3: 255 x 255");
        A = 8'd255;
        B = 8'd255;
        start = 1;
        #20;
        start = 0;
        wait(done == 1);
        #20;
        
        if (P == 16'd65025)
            $display("PASS - Resultado: %d", P);
        else
            $display("FAIL - Esperado: 65025, Obtenido: %d", P);
        
        #100;
        
        //Despuès el test 4: multiplicacion por 0
        $display("Test 4: 100 x 0");
        A = 8'd100;
        B = 8'd0;
        start = 1;
        #20;
        start = 0;
        wait(done == 1);
        #20;
        
        if (P == 16'd0)
            $display("PASS - Resultado: %d", P);
        else
            $display("FAIL - Esperado: 0, Obtenido: %d", P);
        
        #100;
        
        // Y por el ùltimo el test 5: 15 x 7
        $display("Test 5: 15 x 7");
        A = 8'd15;
        B = 8'd7;
        start = 1;
        #20;
        start = 0;
        wait(done == 1);
        #20;
        
        if (P == 16'd105)
            $display("PASS - Resultado: %d", P);
        else
            $display("FAIL - Esperado: 105, Obtenido: %d", P);
        
        #200;
        
        $display("Fin de pruebas");
        $finish;
    end
    
    initial begin
        $monitor("t=%0t | A=%d B=%d | P=%d | busy=%b done=%b", 
                 $time, A, B, P, busy, done);
    end

endmodule

Codigos Calculadora/multiplicador/multiplicador.vcd
$date
	Sun Nov 23 08:56:10 2025
$end
$version
	Icarus Verilog
$end
$timescale
	1ps
$end
$scope module tb_mult $end
$var wire 1 ! done $end
$var wire 1 " busy $end
$var wire 16 # P [15:0] $end
$var reg 8 $ A [7:0] $end
$var reg 8 % B [7:0] $end
$var reg 1 & clk $end
$var reg 1 ' reset $end
$var reg 1 ( start $end
$scope module dut $end
$var wire 8 ) A [7:0] $end
$var wire 8 * B [7:0] $end
$var wire 1 & clk $end
$var wire 1 ' reset $end
$var wire 1 ( start $end
$var wire 1 + shift $end
$var wire 1 , load $end
$var wire 1 ! done $end
$var wire 1 - dec_count $end
$var wire 1 . count_zero $end
$var wire 1 / clear_P $end
$var wire 1 " busy $end
$var wire 1 0 add $end
$var wire 16 1 P [15:0] $end
$var wire 1 2 B_bit0 $end
$scope module datapath $end
$var wire 8 3 A_in [7:0] $end
$var wire 8 4 B_in [7:0] $end
$var wire 8 5 B_reg_out [7:0] $end
$var wire 1 & clk $end
$var wire 1 ' reset $end
$var wire 1 + shift $end
$var wire 1 , load $end
$var wire 1 - dec_count $end
$var wire 1 . count_zero $end
$var wire 1 / clear_P $end
$var wire 1 0 add $end
$var wire 1 2 B_bit0 $end
$var wire 8 6 A_reg_out [7:0] $end
$var reg 16 7 A_reg [15:0] $end
$var reg 8 8 B_reg [7:0] $end
$var reg 16 9 P [15:0] $end
$var reg 4 : count [3:0] $end
$upscope $end
$scope module fsm $end
$var wire 1 2 B_bit0 $end
$var wire 1 & clk $end
$var wire 1 . count_zero $end
$var wire 1 ' reset $end
$var wire 1 ( start $end
$var parameter 3 ; ADD $end
$var parameter 3 < CHECK $end
$var parameter 3 = DONE_ST $end
$var parameter 3 > IDLE $end
$var parameter 3 ? LOAD $end
$var parameter 3 @ SHIFT $end
$var reg 1 0 add $end
$var reg 1 " busy $end
$var reg 1 / clear_P $end
$var reg 1 - dec_count $end
$var reg 1 ! done $end
$var reg 1 , load $end
$var reg 3 A next_state [2:0] $end
$var reg 1 + shift $end
$var reg 3 B state [2:0] $end
$upscope $end
$upscope $end
$upscope $end
$enddefinitions $end
$comment Show the parameter values. $end
$dumpall
b100 @
b1 ?
b0 >
b101 =
b10 <
b11 ;
$end
#0
$dumpvars
b0 B
b0 A
b0 :
b0 9
b0 8
b0 7
b0 6
b0 5
b0 4
b0 3
02
b0 1
00
0/
1.
0-
0,
0+
b0 *
b0 )
0(
1'
0&
b0 %
b0 $
b0 #
0"
0!
$end
#10000
1&
#20000
0&
#30000
1&
#40000
0&
#50000
1&
0'
#60000
0&
#70000
1"
1/
1,
b1 B
b10 A
1&
1(
b11 %
b11 *
b11 4
b101 $
b101 )
b101 3
#80000
0&
#90000
1"
0/
0,
12
b101 6
b10 B
0.
b1000 :
b11 5
b11 8
b101 7
b11 A
1&
0(
#100000
0&
#110000
10
1"
b100 A
b11 B
1&
#120000
0&
#130000
1-
1+
1"
00
b10 A
b100 B
b101 #
b101 1
b101 9
1&
#140000
0&
#150000
b1010 6
1"
0-
0+
b11 A
b111 :
b1 5
b1 8
b1010 7
b10 B
1&
#160000
0&
#170000
10
1"
b100 A
b11 B
1&
#180000
0&
#190000
1-
1+
1"
00
b10 A
b1111 #
b1111 1
b1111 9
b100 B
1&
#200000
0&
#210000
1"
0-
0+
b100 A
02
b10100 6
b10 B
b110 :
b0 5
b0 8
b10100 7
1&
#220000
0&
#230000
1-
1+
1"
b10 A
b100 B
1&
#240000
0&
#250000
1"
0-
0+
b100 A
b101000 6
b10 B
b101 :
b101000 7
1&
#260000
0&
#270000
1-
1+
1"
b10 A
b100 B
1&
#280000
0&
#290000
1"
0-
0+
b100 A
b1010000 6
b10 B
b100 :
b1010000 7
1&
#300000
0&
#310000
1-
1+
1"
b10 A
b100 B
1&
#320000
0&
#330000
1"
0-
0+
b100 A
b10100000 6
b10 B
b11 :
b10100000 7
1&
#340000
0&
#350000
1-
1+
1"
b10 A
b100 B
1&
#360000
0&
#370000
1"
0-
0+
b100 A
b1000000 6
b10 B
b10 :
b101000000 7
1&
#380000
0&
#390000
1-
1+
1"
b10 A
b100 B
1&
#400000
0&
#410000
1"
0-
0+
b100 A
b10000000 6
b10 B
b1 :
b1010000000 7
1&
#420000
0&
#430000
1-
1+
1"
b10 A
b100 B
1&
#440000
0&
#450000
1"
0-
0+
b100 A
b0 6
b10 B
1.
b0 :
b10100000000 7
1&
#460000
0&
#470000
1-
1+
1"
b101 A
b100 B
1&
#480000
0&
#490000
1!
0"
0-
0+
b0 A
b101 B
0.
b1111 :
b101000000000 7
1&
#500000
0&
#510000
0!
b0 B
1&
#520000
0&
#530000
1&
#540000
0&
#550000
1&
#560000
0&
#570000
1&
#580000
0&
#590000
1&
#600000
0&
#610000
1"
1/
1,
b1 B
b10 A
1&
1(
b1000 %
b1000 *
b1000 4
b1100 $
b1100 )
b1100 3
#620000
0&
#630000
b1100 6
1"
0/
0,
b0 #
b0 1
b0 9
b1000 :
b1000 5
b1000 8
b1100 7
b10 B
b100 A
1&
0(
#640000
0&
#650000
1-
1+
1"
b10 A
b100 B
1&
#660000
0&
#670000
b11000 6
1"
0-
0+
b100 A
b111 :
b100 5
b100 8
b11000 7
b10 B
1&
#680000
0&
#690000
1-
1+
1"
b10 A
b100 B
1&
#700000
0&
#710000
b110000 6
1"
0-
0+
b100 A
b110 :
b10 5
b10 8
b110000 7
b10 B
1&
#720000
0&
#730000
1-
1+
1"
b10 A
b100 B
1&
#740000
0&
#750000
12
b1100000 6
1"
0-
0+
b11 A
b101 :
b1 5
b1 8
b1100000 7
b10 B
1&
#760000
0&
#770000
10
1"
b100 A
b11 B
1&
#780000
0&
#790000
1-
1+
1"
00
b10 A
b1100000 #
b1100000 1
b1100000 9
b100 B
1&
#800000
0&
#810000
1"
0-
0+
b100 A
02
b11000000 6
b10 B
b100 :
b0 5
b0 8
b11000000 7
1&
#820000
0&
#830000
1-
1+
1"
b10 A
b100 B
1&
#840000
0&
#850000
1"
0-
0+
b100 A
b10000000 6
b10 B
b11 :
b110000000 7
1&
#860000
0&
#870000
1-
1+
1"
b10 A
b100 B
1&
#880000
0&
#890000
1"
0-
0+
b100 A
b0 6
b10 B
b10 :
b1100000000 7
1&
#900000
0&
#910000
1-
1+
1"
b10 A
b100 B
1&
#920000
0&
#930000
1"
0-
0+
b100 A
b10 B
b1 :
b11000000000 7
1&
#940000
0&
#950000
1-
1+
1"
b10 A
b100 B
1&
#960000
0&
#970000
1"
0-
0+
b100 A
b10 B
1.
b0 :
b110000000000 7
1&
#980000
0&
#990000
1-
1+
1"
b101 A
b100 B
1&
#1000000
0&
#1010000
1!
0"
0-
0+
b0 A
b101 B
0.
b1111 :
b1100000000000 7
1&
#1020000
0&
#1030000
0!
b0 B
1&
#1040000
0&
#1050000
1&
#1060000
0&
#1070000
1&
#1080000
0&
#1090000
1&
#1100000
0&
#1110000
1&
#1120000
0&
#1130000
1"
1/
1,
b1 B
b10 A
1&
1(
b11111111 %
b11111111 *
b11111111 4
b11111111 $
b11111111 )
b11111111 3
#1140000
0&
#1150000
12
b11111111 6
1"
0/
0,
b0 #
b0 1
b0 9
b1000 :
b11111111 5
b11111111 8
b11111111 7
b10 B
b11 A
1&
0(
#1160000
0&
#1170000
10
1"
b100 A
b11 B
1&
#1180000
0&
#1190000
1-
1+
1"
00
b10 A
b11111111 #
b11111111 1
b11111111 9
b100 B
1&
#1200000
0&
#1210000
1"
0-
0+
b11 A
b11111110 6
b10 B
b111 :
b1111111 5
b1111111 8
b111111110 7
1&
#1220000
0&
#1230000
10
1"
b100 A
b11 B
1&
#1240000
0&
#1250000
1-
1+
1"
00
b10 A
b100 B
b1011111101 #
b1011111101 1
b1011111101 9
1&
#1260000
0&
#1270000
b11111100 6
1"
0-
0+
b11 A
b110 :
b111111 5
b111111 8
b1111111100 7
b10 B
1&
#1280000
0&
#1290000
10
1"
b100 A
b11 B
1&
#1300000
0&
#1310000
1-
1+
1"
00
b10 A
b11011111001 #
b11011111001 1
b11011111001 9
b100 B
1&
#1320000
0&
#1330000
1"
0-
0+
b11 A
b11111000 6
b10 B
b101 :
b11111 5
b11111 8
b11111111000 7
1&
#1340000
0&
#1350000
10
1"
b100 A
b11 B
1&
#1360000
0&
#1370000
1-
1+
1"
00
b10 A
b100 B
b111011110001 #
b111011110001 1
b111011110001 9
1&
#1380000
0&
#1390000
b11110000 6
1"
0-
0+
b11 A
b100 :
b1111 5
b1111 8
b111111110000 7
b10 B
1&
#1400000
0&
#1410000
10
1"
b100 A
b11 B
1&
#1420000
0&
#1430000
1-
1+
1"
00
b10 A
b1111011100001 #
b1111011100001 1
b1111011100001 9
b100 B
1&
#1440000
0&
#1450000
1"
0-
0+
b11 A
b11100000 6
b10 B
b11 :
b111 5
b111 8
b1111111100000 7
1&
#1460000
0&
#1470000
10
1"
b100 A
b11 B
1&
#1480000
0&
#1490000
1-
1+
1"
00
b10 A
b100 B
b11111011000001 #
b11111011000001 1
b11111011000001 9
1&
#1500000
0&
#1510000
b11000000 6
1"
0-
0+
b11 A
b10 :
b11 5
b11 8
b11111111000000 7
b10 B
1&
#1520000
0&
#1530000
10
1"
b100 A
b11 B
1&
#1540000
0&
#1550000
1-
1+
1"
00
b10 A
b111111010000001 #
b111111010000001 1
b111111010000001 9
b100 B
1&
#1560000
0&
#1570000
1"
0-
0+
b11 A
b10000000 6
b10 B
b1 :
b1 5
b1 8
b111111110000000 7
1&
#1580000
0&
#1590000
10
1"
b100 A
b11 B
1&
#1600000
0&
#1610000
1-
1+
1"
00
b10 A
b100 B
b1111111000000001 #
b1111111000000001 1
b1111111000000001 9
1&
#1620000
0&
#1630000
02
b0 6
1"
0-
0+
b100 A
1.
b0 :
b0 5
b0 8
b1111111100000000 7
b10 B
1&
#1640000
0&
#1650000
1-
1+
1"
b101 A
b100 B
1&
#1660000
0&
#1670000
1!
0"
0-
0+
b0 A
0.
b1111 :
b1111111000000000 7
b101 B
1&
#1680000
0&
#1690000
0!
b0 B
1&
#1700000
0&
#1710000
1&
#1720000
0&
#1730000
1&
#1740000
0&
#1750000
1&
#1760000
0&
#1770000
1&
#1780000
0&
#1790000
1"
1/
1,
b1 B
b10 A
1&
1(
b0 %
b0 *
b0 4
b1100100 $
b1100100 )
b1100100 3
#1800000
0&
#1810000
1"
0/
0,
b1100100 6
b10 B
b0 #
b0 1
b0 9
b1000 :
b1100100 7
b100 A
1&
0(
#1820000
0&
#1830000
1-
1+
1"
b10 A
b100 B
1&
#1840000
0&
#1850000
1"
0-
0+
b100 A
b11001000 6
b10 B
b111 :
b11001000 7
1&
#1860000
0&
#1870000
1-
1+
1"
b10 A
b100 B
1&
#1880000
0&
#1890000
1"
0-
0+
b100 A
b10010000 6
b10 B
b110 :
b110010000 7
1&
#1900000
0&
#1910000
1-
1+
1"
b10 A
b100 B
1&
#1920000
0&
#1930000
1"
0-
0+
b100 A
b100000 6
b10 B
b101 :
b1100100000 7
1&
#1940000
0&
#1950000
1-
1+
1"
b10 A
b100 B
1&
#1960000
0&
#1970000
1"
0-
0+
b100 A
b1000000 6
b10 B
b100 :
b11001000000 7
1&
#1980000
0&
#1990000
1-
1+
1"
b10 A
b100 B
1&
#2000000
0&
#2010000
1"
0-
0+
b100 A
b10000000 6
b10 B
b11 :
b110010000000 7
1&
#2020000
0&
#2030000
1-
1+
1"
b10 A
b100 B
1&
#2040000
0&
#2050000
1"
0-
0+
b100 A
b0 6
b10 B
b10 :
b1100100000000 7
1&
#2060000
0&
#2070000
1-
1+
1"
b10 A
b100 B
1&
#2080000
0&
#2090000
1"
0-
0+
b100 A
b10 B
b1 :
b11001000000000 7
1&
#2100000
0&
#2110000
1-
1+
1"
b10 A
b100 B
1&
#2120000
0&
#2130000
1"
0-
0+
b100 A
b10 B
1.
b0 :
b110010000000000 7
1&
#2140000
0&
#2150000
1-
1+
1"
b101 A
b100 B
1&
#2160000
0&
#2170000
1!
0"
0-
0+
b0 A
b101 B
0.
b1111 :
b1100100000000000 7
1&
#2180000
0&
#2190000
0!
b0 B
1&
#2200000
0&
#2210000
1&
#2220000
0&
#2230000
1&
#2240000
0&
#2250000
1&
#2260000
0&
#2270000
1&
#2280000
0&
#2290000
1"
1/
1,
b1 B
b10 A
1&
1(
b111 %
b111 *
b111 4
b1111 $
b1111 )
b1111 3
#2300000
0&
#2310000
12
b1111 6
1"
0/
0,
b1000 :
b111 5
b111 8
b1111 7
b10 B
b11 A
1&
0(
#2320000
0&
#2330000
10
1"
b100 A
b11 B
1&
#2340000
0&
#2350000
1-
1+
1"
00
b10 A
b1111 #
b1111 1
b1111 9
b100 B
1&
#2360000
0&
#2370000
1"
0-
0+
b11 A
b11110 6
b10 B
b111 :
b11 5
b11 8
b11110 7
1&
#2380000
0&
#2390000
10
1"
b100 A
b11 B
1&
#2400000
0&
#2410000
1-
1+
1"
00
b10 A
b100 B
b101101 #
b101101 1
b101101 9
1&
#2420000
0&
#2430000
b111100 6
1"
0-
0+
b11 A
b110 :
b1 5
b1 8
b111100 7
b10 B
1&
#2440000
0&
#2450000
10
1"
b100 A
b11 B
1&
#2460000
0&
#2470000
1-
1+
1"
00
b10 A
b1101001 #
b1101001 1
b1101001 9
b100 B
1&
#2480000
0&
#2490000
1"
0-
0+
b100 A
02
b1111000 6
b10 B
b101 :
b0 5
b0 8
b1111000 7
1&
#2500000
0&
#2510000
1-
1+
1"
b10 A
b100 B
1&
#2520000
0&
#2530000
1"
0-
0+
b100 A
b11110000 6
b10 B
b100 :
b11110000 7
1&
#2540000
0&
#2550000
1-
1+
1"
b10 A
b100 B
1&
#2560000
0&
#2570000
1"
0-
0+
b100 A
b11100000 6
b10 B
b11 :
b111100000 7
1&
#2580000
0&
#2590000
1-
1+
1"
b10 A
b100 B
1&
#2600000
0&
#2610000
1"
0-
0+
b100 A
b11000000 6
b10 B
b10 :
b1111000000 7
1&
#2620000
0&
#2630000
1-
1+
1"
b10 A
b100 B
1&
#2640000
0&
#2650000
1"
0-
0+
b100 A
b10000000 6
b10 B
b1 :
b11110000000 7
1&
#2660000
0&
#2670000
1-
1+
1"
b10 A
b100 B
1&
#2680000
0&
#2690000
1"
0-
0+
b100 A
b0 6
b10 B
1.
b0 :
b111100000000 7
1&
#2700000
0&
#2710000
1-
1+
1"
b101 A
b100 B
1&
#2720000
0&
#2730000
1!
0"
0-
0+
b0 A
b101 B
0.
b1111 :
b1111000000000 7
1&
#2740000
0&
#2750000
0!
b0 B
1&
