divisor/rtl/control_div.v
// FSM para control del divisor - restas secuenciales
module control_div (
    input wire clk,
    input wire reset,
    input wire start,
    input wire div_zero,
    input wire R_gte_B,
    output reg load,
    output reg subtract,
    output reg inc_Q,
    output reg busy,
    output reg done
);

    localparam [2:0] 
        IDLE       = 3'd0,
        LOAD       = 3'd1,
        CHECK_ZERO = 3'd2,
        CHECK      = 3'd3,
        SUBTRACT   = 3'd4,
        DONE_ST    = 3'd5;
    
    reg [2:0] state, next_state;
    
    always @(posedge clk or posedge reset) begin
        if (reset)
            state <= IDLE;
        else
            state <= next_state;
    end
    
    always @(*) begin
        next_state = state;
        
        case (state)
            IDLE: begin
                if (start)
                    next_state = LOAD;
            end
            
            LOAD: begin
                next_state = CHECK_ZERO;
            end
            
            CHECK_ZERO: begin
                if (div_zero)
                    next_state = DONE_ST;
                else
                    next_state = CHECK;
            end
            
            CHECK: begin
                if (R_gte_B)
                    next_state = SUBTRACT;
                else
                    next_state = DONE_ST;
            end
            
            SUBTRACT: begin
                next_state = CHECK;
            end
            
            DONE_ST: begin
                next_state = IDLE;
            end
            
            default: begin
                next_state = IDLE;
            end
        endcase
    end
    
    always @(*) begin
        load = 1'b0;
        subtract = 1'b0;
        inc_Q = 1'b0;
        busy = 1'b0;
        done = 1'b0;
        
        case (state)
            IDLE: begin
                busy = 1'b0;
                done = 1'b0;
            end
            
            LOAD: begin
                load = 1'b1;
                busy = 1'b1;
            end
            
            CHECK_ZERO: begin
                busy = 1'b1;
            end
            
            CHECK: begin
                busy = 1'b1;
            end
            
            SUBTRACT: begin
                subtract = 1'b1;
                inc_Q = 1'b1;
                busy = 1'b1;
            end
            
            DONE_ST: begin
                done = 1'b1;
                busy = 1'b0;
            end
            
            default: begin
                busy = 1'b0;
                done = 1'b0;
            end
        endcase
    end

endmodule

divisor/rtl/dp_div.v
// Datapath del divisor - metodo de restas secuenciales
module dp_div (
    input wire clk,
    input wire reset,
    input wire [7:0] A_in,
    input wire [7:0] B_in,
    input wire load,
    input wire subtract,
    input wire inc_Q,
    output reg [7:0] Q,
    output reg [7:0] R,
    output wire div_zero,
    output wire R_gte_B
);

    reg [7:0] B_reg;
    
    assign div_zero = (B_reg == 8'd0);
    assign R_gte_B = (R >= B_reg);
    
    always @(posedge clk or posedge reset) begin
        if (reset) begin
            Q <= 8'd0;
            R <= 8'd0;
            B_reg <= 8'd0;
        end 
        else begin
            if (load) begin
                R <= A_in;
                Q <= 8'd0;
                B_reg <= B_in;
            end
            
            if (subtract) begin
                R <= R - B_reg;
            end
            
            if (inc_Q) begin
                Q <= Q + 1;
            end
        end
    end

endmodule

divisor/rtl/div_top.v

// Módulo superior del divisor 8÷8

module div_top (
    input  wire        clk,
    input  wire        reset,
    input  wire        start,
    input  wire [7:0]  A,
    input  wire [7:0]  B,
    output wire [7:0]  Q,
    output wire [7:0]  R,
    output wire        busy,
    output wire        done,
    output wire        div_zero
);

    wire load;
    wire subtract;
    wire inc_Q;
    wire R_gte_B;

    dp_div datapath (
        .clk(clk),
        .reset(reset),
        .A_in(A),
        .B_in(B),
        .load(load),
        .subtract(subtract),
        .inc_Q(inc_Q),
        .Q(Q),
        .R(R),
        .div_zero(div_zero),
        .R_gte_B(R_gte_B)
    );

    control_div fsm (
        .clk(clk),
        .reset(reset),
        .start(start),
        .div_zero(div_zero),
        .R_gte_B(R_gte_B),
        .load(load),
        .subtract(subtract),
        .inc_Q(inc_Q),
        .busy(busy),
        .done(done)
    );

endmodule

Codigos Calculadora/entrega_final/simulacion/tb_div.v
`timescale 1ns/1ps

module tb_div;

    reg clk;
    reg reset;
    reg start;
    reg [7:0] A;
    reg [7:0] B;
    wire [7:0] Q;
    wire [7:0] R;
    wire busy;
    wire done;
    wire div_zero;
    
    div_top dut (
        .clk(clk),
        .reset(reset),
        .start(start),
        .A(A),
        .B(B),
        .Q(Q),
        .R(R),
        .busy(busy),
        .done(done),
        .div_zero(div_zero)
    );
    
    initial begin
        clk = 0;
        forever #10 clk = ~clk;
    end
    
    initial begin
        reset = 1;
        start = 0;
        A = 8'd0;
        B = 8'd0;
        
        $dumpfile("divisor.vcd");
        $dumpvars(0, tb_div);
        
        $display("Inicio de pruebas - Divisor");
        
        #50;
        reset = 0;
        #20;
        
        // Test 1: 15 / 3 = 5, residuo 0
        $display("\nTest 1: 15 / 3");
        A = 8'd15;
        B = 8'd3;
        start = 1;
        #20;
        start = 0;
        wait(done == 1);
        #20;
        
        if (Q == 8'd5 && R == 8'd0)
            $display("PASS - Cociente: %d, Residuo: %d", Q, R);
        else
            $display("FAIL - Esperado: Q=5 R=0, Obtenido: Q=%d R=%d", Q, R);
        
        #100;
        
        // Test 2: 20 / 4 = 5, residuo 0
        $display("\nTest 2: 20 / 4");
        A = 8'd20;
        B = 8'd4;
        start = 1;
        #20;
        start = 0;
        wait(done == 1);
        #20;
        
        if (Q == 8'd5 && R == 8'd0)
            $display("PASS - Cociente: %d, Residuo: %d", Q, R);
        else
            $display("FAIL - Esperado: Q=5 R=0, Obtenido: Q=%d R=%d", Q, R);
        
        #100;
        
        // Test 3: 17 / 5 = 3, residuo 2
        $display("\nTest 3: 17 / 5");
        A = 8'd17;
        B = 8'd5;
        start = 1;
        #20;
        start = 0;
        wait(done == 1);
        #20;
        
        if (Q == 8'd3 && R == 8'd2)
            $display("PASS - Cociente: %d, Residuo: %d", Q, R);
        else
            $display("FAIL - Esperado: Q=3 R=2, Obtenido: Q=%d R=%d", Q, R);
        
        #100;
        
        // Test 4: 255 / 10 = 25, residuo 5
        $display("\nTest 4: 255 / 10");
        A = 8'd255;
        B = 8'd10;
        start = 1;
        #20;
        start = 0;
        wait(done == 1);
        #20;
        
        if (Q == 8'd25 && R == 8'd5)
            $display("PASS - Cociente: %d, Residuo: %d", Q, R);
        else
            $display("FAIL - Esperado: Q=25 R=5, Obtenido: Q=%d R=%d", Q, R);
        
        #100;
        
        // Test 5: division por cero 100 / 0
        $display("\nTest 5: 100 / 0 (div por cero)");
        A = 8'd100;
        B = 8'd0;
        start = 1;
        #20;
        start = 0;
        wait(done == 1);
        #20;
        
        if (div_zero == 1'b1)
            $display("PASS - Flag div_zero activo");
        else
            $display("FAIL - Flag div_zero debería estar activo");
        
        #200;
        
        $display("\nFin de pruebas");
        $finish;
    end
    
    initial begin
        $monitor("t=%0t | A=%d B=%d | Q=%d R=%d | busy=%b done=%b div_zero=%b", 
                 $time, A, B, Q, R, busy, done, div_zero);
    end

endmodule

divisor/divisor.vcd
$date
	Sun Nov 23 22:38:49 2025
$end
$version
	Icarus Verilog
$end
$timescale
	1ps
$end
$scope module tb_div $end
$var wire 1 ! done $end
$var wire 1 " div_zero $end
$var wire 1 # busy $end
$var wire 8 $ R [7:0] $end
$var wire 8 % Q [7:0] $end
$var reg 8 & A [7:0] $end
$var reg 8 ' B [7:0] $end
$var reg 1 ( clk $end
$var reg 1 ) reset $end
$var reg 1 * start $end
$scope module dut $end
$var wire 8 + A [7:0] $end
$var wire 8 , B [7:0] $end
$var wire 1 ( clk $end
$var wire 1 ) reset $end
$var wire 1 * start $end
$var wire 1 - subtract $end
$var wire 1 . load $end
$var wire 1 / inc_Q $end
$var wire 1 ! done $end
$var wire 1 " div_zero $end
$var wire 1 # busy $end
$var wire 1 0 R_gte_B $end
$var wire 8 1 R [7:0] $end
$var wire 8 2 Q [7:0] $end
$scope module datapath $end
$var wire 8 3 A_in [7:0] $end
$var wire 8 4 B_in [7:0] $end
$var wire 1 ( clk $end
$var wire 1 ) reset $end
$var wire 1 - subtract $end
$var wire 1 . load $end
$var wire 1 / inc_Q $end
$var wire 1 " div_zero $end
$var wire 1 0 R_gte_B $end
$var reg 8 5 B_reg [7:0] $end
$var reg 8 6 Q [7:0] $end
$var reg 8 7 R [7:0] $end
$upscope $end
$scope module fsm $end
$var wire 1 0 R_gte_B $end
$var wire 1 ( clk $end
$var wire 1 " div_zero $end
$var wire 1 ) reset $end
$var wire 1 * start $end
$var parameter 3 8 CHECK $end
$var parameter 3 9 CHECK_ZERO $end
$var parameter 3 : DONE_ST $end
$var parameter 3 ; IDLE $end
$var parameter 3 < LOAD $end
$var parameter 3 = SUBTRACT $end
$var reg 1 # busy $end
$var reg 1 ! done $end
$var reg 1 / inc_Q $end
$var reg 1 . load $end
$var reg 3 > next_state [2:0] $end
$var reg 3 ? state [2:0] $end
$var reg 1 - subtract $end
$upscope $end
$upscope $end
$upscope $end
$enddefinitions $end
$comment Show the parameter values. $end
$dumpall
b100 =
b1 <
b0 ;
b101 :
b10 9
b11 8
$end
#0
$dumpvars
b0 ?
b0 >
b0 7
b0 6
b0 5
b0 4
b0 3
b0 2
b0 1
10
0/
0.
0-
b0 ,
b0 +
0*
1)
0(
b0 '
b0 &
b0 %
b0 $
0#
1"
0!
$end
#10000
1(
#20000
0(
#30000
1(
#40000
0(
#50000
1(
0)
#60000
0(
#70000
1#
1.
b1 ?
b10 >
1(
1*
b11 '
b11 ,
b11 4
b1111 &
b1111 +
b1111 3
#80000
0(
#90000
1#
0.
b10 ?
0"
b11 5
b1111 $
b1111 1
b1111 7
b11 >
1(
0*
#100000
0(
#110000
1#
b100 >
b11 ?
1(
#120000
0(
#130000
1/
1-
1#
b11 >
b100 ?
1(
#140000
0(
#150000
1#
0/
0-
b100 >
b1 %
b1 2
b1 6
b1100 $
b1100 1
b1100 7
b11 ?
1(
#160000
0(
#170000
1/
1-
1#
b11 >
b100 ?
1(
#180000
0(
#190000
1#
0/
0-
b100 >
b10 %
b10 2
b10 6
b1001 $
b1001 1
b1001 7
b11 ?
1(
#200000
0(
#210000
1/
1-
1#
b11 >
b100 ?
1(
#220000
0(
#230000
1#
0/
0-
b100 >
b11 %
b11 2
b11 6
b110 $
b110 1
b110 7
b11 ?
1(
#240000
0(
#250000
1/
1-
1#
b11 >
b100 ?
1(
#260000
0(
#270000
1#
0/
0-
b100 >
b100 %
b100 2
b100 6
b11 $
b11 1
b11 7
b11 ?
1(
#280000
0(
#290000
1/
1-
1#
b11 >
b100 ?
1(
#300000
0(
#310000
1#
0/
0-
b101 >
b101 %
b101 2
b101 6
00
b0 $
b0 1
b0 7
b11 ?
1(
#320000
0(
#330000
1!
0#
b0 >
b101 ?
1(
#340000
0(
#350000
0!
b0 ?
1(
#360000
0(
#370000
1(
#380000
0(
#390000
1(
#400000
0(
#410000
1(
#420000
0(
#430000
1(
#440000
0(
#450000
1#
1.
b1 ?
b10 >
1(
1*
b100 '
b100 ,
b100 4
b10100 &
b10100 +
b10100 3
#460000
0(
#470000
1#
0.
b100 5
b0 %
b0 2
b0 6
10
b10100 $
b10100 1
b10100 7
b10 ?
b11 >
1(
0*
#480000
0(
#490000
1#
b100 >
b11 ?
1(
#500000
0(
#510000
1/
1-
1#
b11 >
b100 ?
1(
#520000
0(
#530000
1#
0/
0-
b100 >
b11 ?
b1 %
b1 2
b1 6
b10000 $
b10000 1
b10000 7
1(
#540000
0(
#550000
1/
1-
1#
b11 >
b100 ?
1(
#560000
0(
#570000
1#
0/
0-
b100 >
b11 ?
b10 %
b10 2
b10 6
b1100 $
b1100 1
b1100 7
1(
#580000
0(
#590000
1/
1-
1#
b11 >
b100 ?
1(
#600000
0(
#610000
1#
0/
0-
b100 >
b11 ?
b11 %
b11 2
b11 6
b1000 $
b1000 1
b1000 7
1(
#620000
0(
#630000
1/
1-
1#
b11 >
b100 ?
1(
#640000
0(
#650000
1#
0/
0-
b100 >
b11 ?
b100 %
b100 2
b100 6
b100 $
b100 1
b100 7
1(
#660000
0(
#670000
1/
1-
1#
b11 >
b100 ?
1(
#680000
0(
#690000
1#
0/
0-
b101 >
b11 ?
b101 %
b101 2
b101 6
00
b0 $
b0 1
b0 7
1(
#700000
0(
#710000
1!
0#
b0 >
b101 ?
1(
#720000
0(
#730000
0!
b0 ?
1(
#740000
0(
#750000
1(
#760000
0(
#770000
1(
#780000
0(
#790000
1(
#800000
0(
#810000
1(
#820000
0(
#830000
1#
1.
b1 ?
b10 >
1(
1*
b101 '
b101 ,
b101 4
b10001 &
b10001 +
b10001 3
#840000
0(
#850000
1#
0.
b10 ?
b101 5
b0 %
b0 2
b0 6
10
b10001 $
b10001 1
b10001 7
b11 >
1(
0*
#860000
0(
#870000
1#
b100 >
b11 ?
1(
#880000
0(
#890000
1/
1-
1#
b11 >
b100 ?
1(
#900000
0(
#910000
1#
0/
0-
b100 >
b1 %
b1 2
b1 6
b1100 $
b1100 1
b1100 7
b11 ?
1(
#920000
0(
#930000
1/
1-
1#
b11 >
b100 ?
1(
#940000
0(
#950000
1#
0/
0-
b100 >
b10 %
b10 2
b10 6
b111 $
b111 1
b111 7
b11 ?
1(
#960000
0(
#970000
1/
1-
1#
b11 >
b100 ?
1(
#980000
0(
#990000
1#
0/
0-
b101 >
b11 %
b11 2
b11 6
00
b10 $
b10 1
b10 7
b11 ?
1(
#1000000
0(
#1010000
1!
0#
b0 >
b101 ?
1(
#1020000
0(
#1030000
0!
b0 ?
1(
#1040000
0(
#1050000
1(
#1060000
0(
#1070000
1(
#1080000
0(
#1090000
1(
#1100000
0(
#1110000
1(
#1120000
0(
#1130000
1#
1.
b1 ?
b10 >
1(
1*
b1010 '
b1010 ,
b1010 4
b11111111 &
b11111111 +
b11111111 3
#1140000
0(
#1150000
1#
0.
b1010 5
b0 %
b0 2
b0 6
10
b11111111 $
b11111111 1
b11111111 7
b10 ?
b11 >
1(
0*
#1160000
0(
#1170000
1#
b100 >
b11 ?
1(
#1180000
0(
#1190000
1/
1-
1#
b11 >
b100 ?
1(
#1200000
0(
#1210000
1#
0/
0-
b100 >
b11 ?
b1 %
b1 2
b1 6
b11110101 $
b11110101 1
b11110101 7
1(
#1220000
0(
#1230000
1/
1-
1#
b11 >
b100 ?
1(
#1240000
0(
#1250000
1#
0/
0-
b100 >
b11 ?
b10 %
b10 2
b10 6
b11101011 $
b11101011 1
b11101011 7
1(
#1260000
0(
#1270000
1/
1-
1#
b11 >
b100 ?
1(
#1280000
0(
#1290000
1#
0/
0-
b100 >
b11 ?
b11 %
b11 2
b11 6
b11100001 $
b11100001 1
b11100001 7
1(
#1300000
0(
#1310000
1/
1-
1#
b11 >
b100 ?
1(
#1320000
0(
#1330000
1#
0/
0-
b100 >
b11 ?
b100 %
b100 2
b100 6
b11010111 $
b11010111 1
b11010111 7
1(
#1340000
0(
#1350000
1/
1-
1#
b11 >
b100 ?
1(
#1360000
0(
#1370000
1#
0/
0-
b100 >
b11 ?
b101 %
b101 2
b101 6
b11001101 $
b11001101 1
b11001101 7
1(
#1380000
0(
#1390000
1/
1-
1#
b11 >
b100 ?
1(
#1400000
0(
#1410000
1#
0/
0-
b100 >
b11 ?
b110 %
b110 2
b110 6
b11000011 $
b11000011 1
b11000011 7
1(
#1420000
0(
#1430000
1/
1-
1#
b11 >
b100 ?
1(
#1440000
0(
#1450000
1#
0/
0-
b100 >
b11 ?
b111 %
b111 2
b111 6
b10111001 $
b10111001 1
b10111001 7
1(
#1460000
0(
#1470000
1/
1-
1#
b11 >
b100 ?
1(
#1480000
0(
#1490000
1#
0/
0-
b100 >
b11 ?
b1000 %
b1000 2
b1000 6
b10101111 $
b10101111 1
b10101111 7
1(
#1500000
0(
#1510000
1/
1-
1#
b11 >
b100 ?
1(
#1520000
0(
#1530000
1#
0/
0-
b100 >
b11 ?
b1001 %
b1001 2
b1001 6
b10100101 $
b10100101 1
b10100101 7
1(
#1540000
0(
#1550000
1/
1-
1#
b11 >
b100 ?
1(
#1560000
0(
#1570000
1#
0/
0-
b100 >
b11 ?
b1010 %
b1010 2
b1010 6
b10011011 $
b10011011 1
b10011011 7
1(
#1580000
0(
#1590000
1/
1-
1#
b11 >
b100 ?
1(
#1600000
0(
#1610000
1#
0/
0-
b100 >
b11 ?
b1011 %
b1011 2
b1011 6
b10010001 $
b10010001 1
b10010001 7
1(
#1620000
0(
#1630000
1/
1-
1#
b11 >
b100 ?
1(
#1640000
0(
#1650000
1#
0/
0-
b100 >
b11 ?
b1100 %
b1100 2
b1100 6
b10000111 $
b10000111 1
b10000111 7
1(
#1660000
0(
#1670000
1/
1-
1#
b11 >
b100 ?
1(
#1680000
0(
#1690000
1#
0/
0-
b100 >
b11 ?
b1101 %
b1101 2
b1101 6
b1111101 $
b1111101 1
b1111101 7
1(
#1700000
0(
#1710000
1/
1-
1#
b11 >
b100 ?
1(
#1720000
0(
#1730000
1#
0/
0-
b100 >
b11 ?
b1110 %
b1110 2
b1110 6
b1110011 $
b1110011 1
b1110011 7
1(
#1740000
0(
#1750000
1/
1-
1#
b11 >
b100 ?
1(
#1760000
0(
#1770000
1#
0/
0-
b100 >
b11 ?
b1111 %
b1111 2
b1111 6
b1101001 $
b1101001 1
b1101001 7
1(
#1780000
0(
#1790000
1/
1-
1#
b11 >
b100 ?
1(
#1800000
0(
#1810000
1#
0/
0-
b100 >
b11 ?
b10000 %
b10000 2
b10000 6
b1011111 $
b1011111 1
b1011111 7
1(
#1820000
0(
#1830000
1/
1-
1#
b11 >
b100 ?
1(
#1840000
0(
#1850000
1#
0/
0-
b100 >
b11 ?
b10001 %
b10001 2
b10001 6
b1010101 $
b1010101 1
b1010101 7
1(
#1860000
0(
#1870000
1/
1-
1#
b11 >
b100 ?
1(
#1880000
0(
#1890000
1#
0/
0-
b100 >
b11 ?
b10010 %
b10010 2
b10010 6
b1001011 $
b1001011 1
b1001011 7
1(
#1900000
0(
#1910000
1/
1-
1#
b11 >
b100 ?
1(
#1920000
0(
#1930000
1#
0/
0-
b100 >
b11 ?
b10011 %
b10011 2
b10011 6
b1000001 $
b1000001 1
b1000001 7
1(
#1940000
0(
#1950000
1/
1-
1#
b11 >
b100 ?
1(
#1960000
0(
#1970000
1#
0/
0-
b100 >
b11 ?
b10100 %
b10100 2
b10100 6
b110111 $
b110111 1
b110111 7
1(
#1980000
0(
#1990000
1/
1-
1#
b11 >
b100 ?
1(
#2000000
0(
#2010000
1#
0/
0-
b100 >
b11 ?
b10101 %
b10101 2
b10101 6
b101101 $
b101101 1
b101101 7
1(
#2020000
0(
#2030000
1/
1-
1#
b11 >
b100 ?
1(
#2040000
0(
#2050000
1#
0/
0-
b100 >
b11 ?
b10110 %
b10110 2
b10110 6
b100011 $
b100011 1
b100011 7
1(
#2060000
0(
#2070000
1/
1-
1#
b11 >
b100 ?
1(
#2080000
0(
#2090000
1#
0/
0-
b100 >
b11 ?
b10111 %
b10111 2
b10111 6
b11001 $
b11001 1
b11001 7
1(
#2100000
0(
#2110000
1/
1-
1#
b11 >
b100 ?
1(
#2120000
0(
#2130000
1#
0/
0-
b100 >
b11 ?
b11000 %
b11000 2
b11000 6
b1111 $
b1111 1
b1111 7
1(
#2140000
0(
#2150000
1/
1-
1#
b11 >
b100 ?
1(
#2160000
0(
#2170000
1#
0/
0-
b101 >
b11 ?
b11001 %
b11001 2
b11001 6
00
b101 $
b101 1
b101 7
1(
#2180000
0(
#2190000
1!
0#
b0 >
b101 ?
1(
#2200000
0(
#2210000
0!
b0 ?
1(
#2220000
0(
#2230000
1(
#2240000
0(
#2250000
1(
#2260000
0(
#2270000
1(
#2280000
0(
#2290000
1(
#2300000
0(
#2310000
1#
1.
b1 ?
b10 >
1(
1*
b0 '
b0 ,
b0 4
b1100100 &
b1100100 +
b1100100 3
#2320000
0(
#2330000
1#
0.
b10 ?
1"
b0 5
b0 %
b0 2
b0 6
10
b1100100 $
b1100100 1
b1100100 7
b101 >
1(
0*
#2340000
0(
#2350000
1!
0#
b0 >
b101 ?
1(
#2360000
0(
#2370000
0!
b0 ?
1(
